funkiest/__init__.py
funkiest/funk.py
funkiest-0.1.dist-info/METADATA
funkiest-0.1.dist-info/WHEEL
funkiest-0.1.dist-info/top_level.txt
funkiest-0.1.dist-info/RECORD
