Metadata-Version: 2.1
Name: funkiest
Version: 0.1
Summary: The funkiest music in the world!
Home-page: https://github.com/bezabihz/funkiest
Author: Bezabih Z
Author-email: bezabihz@gmail.com
License: MIT
Platform: UNKNOWN
